idds/__init__.py
idds/workflow/__init__.py
idds/workflow/base.py
idds/workflow/datawork.py
idds/workflow/processingwork.py
idds/workflow/utils.py
idds/workflow/version.py
idds/workflow/work.py
idds/workflow/workflow.py
idds/workflowv2/__init__.py
idds/workflowv2/base.py
idds/workflowv2/datawork.py
idds/workflowv2/processingwork.py
idds/workflowv2/tree.py
idds/workflowv2/utils.py
idds/workflowv2/version.py
idds/workflowv2/work.py
idds/workflowv2/workflow.py
idds_workflow-2.0.9.data/data/tools/env/environment.yml
idds_workflow-2.0.9.dist-info/LICENSE.rst
idds_workflow-2.0.9.dist-info/METADATA
idds_workflow-2.0.9.dist-info/WHEEL
idds_workflow-2.0.9.dist-info/top_level.txt
idds_workflow-2.0.9.dist-info/RECORD
